django_admin_shellx/__init__.py
django_admin_shellx/admin.py
django_admin_shellx/apps.py
django_admin_shellx/consumers.py
django_admin_shellx/migrations/0001_initial.py
django_admin_shellx/migrations/__init__.py
django_admin_shellx/models.py
django_admin_shellx/signals.py
django_admin_shellx/static/django_admin_shellx/images/.gitkeep
django_admin_shellx/static/django_admin_shellx/output/terminal.css
django_admin_shellx/static/django_admin_shellx/output/terminal.js
django_admin_shellx/templates/django_admin_shellx/terminal.html
django_admin_shellx/templates/django_admin_shellx/terminal_table.html
django_admin_shellx/urls.py
django_admin_shellx/views.py
django_admin_shellx_custom_admin/__init__.py
django_admin_shellx_custom_admin/admin.py
django_admin_shellx_custom_admin/apps.py
django_admin_shellx-0.3.3.dist-info/LICENSE
django_admin_shellx-0.3.3.dist-info/METADATA
django_admin_shellx-0.3.3.dist-info/WHEEL
django_admin_shellx-0.3.3.dist-info/RECORD
