Metadata-Version: 2.1
Name: django-admin-shellx
Version: 0.3.3
Summary: A Django Admin Shell
Home-page: https://github.com/adinhodovic/django-admin-shellx
License: MIT
Keywords: django,admin,terminal,shell,xterm.js
Author: Adin Hodovic
Author-email: hodovicadin@gmail.com
Requires-Python: >=3.9,<4.0
Classifier: Development Status :: 5 - Production/Stable
Classifier: Environment :: Web Environment
Classifier: Framework :: Django
Classifier: Framework :: Django :: 4.2
Classifier: Framework :: Django :: 5.0
Classifier: Intended Audience :: Developers
Classifier: License :: OSI Approved :: MIT License
Classifier: Operating System :: OS Independent
Classifier: Programming Language :: Python
Classifier: Programming Language :: Python :: 3
Classifier: Programming Language :: Python :: 3.9
Classifier: Programming Language :: Python :: 3.10
Classifier: Programming Language :: Python :: 3.11
Requires-Dist: Django (>=4)
Requires-Dist: channels[daphne] (>=4.0.0,<5.0.0)
Requires-Dist: django-model-utils (>=4)
Project-URL: Documentation, https://github.com/adinhodovic/django-admin-shellx
Project-URL: Repository, https://github.com/adinhodovic/django-admin-shellx
